zwende/__init__.py
zwende/zwende.py
zwende-20190716.1.dist-info/DESCRIPTION.rst
zwende-20190716.1.dist-info/LICENSE.txt
zwende-20190716.1.dist-info/METADATA
zwende-20190716.1.dist-info/RECORD
zwende-20190716.1.dist-info/WHEEL
zwende-20190716.1.dist-info/metadata.json
zwende-20190716.1.dist-info/top_level.txt
